airflow_massivedh_plugin/__init__.py
airflow_massivedh_plugin/massive_plugin.py
airflow_massivedh_plugin-0.0.5.dist-info/METADATA
airflow_massivedh_plugin-0.0.5.dist-info/WHEEL
airflow_massivedh_plugin-0.0.5.dist-info/entry_points.txt
airflow_massivedh_plugin-0.0.5.dist-info/top_level.txt
airflow_massivedh_plugin-0.0.5.dist-info/RECORD
